{
 "charts": [],
 "content": "[{\"id\": \"saas-h1\", \"type\": \"header\", \"data\": {\"text\": \"<span class=\\\"h4\\\"><b>ERPGenex SaaS</b></span><br><span class=\\\"text-muted\\\">Multi-tenant platform control plane</span>\", \"col\": 12}}, {\"id\": \"saas-sc-h\", \"type\": \"header\", \"data\": {\"text\": \"<b>Quick access</b>\", \"col\": 12}}, {\"id\": \"saas-sc0\", \"type\": \"shortcut\", \"data\": {\"shortcut_name\": \"SaaS Tenant\", \"col\": 3}}, {\"id\": \"saas-sc1\", \"type\": \"shortcut\", \"data\": {\"shortcut_name\": \"SaaS Subscription\", \"col\": 3}}, {\"id\": \"saas-sc2\", \"type\": \"shortcut\", \"data\": {\"shortcut_name\": \"Provisioning Request\", \"col\": 3}}, {\"id\": \"saas-sc3\", \"type\": \"shortcut\", \"data\": {\"shortcut_name\": \"SaaS Plan\", \"col\": 3}}, {\"id\": \"saas-sc4\", \"type\": \"shortcut\", \"data\": {\"shortcut_name\": \"SaaS Application\", \"col\": 3}}, {\"id\": \"saas-sc5\", \"type\": \"shortcut\", \"data\": {\"shortcut_name\": \"SaaS Settings\", \"col\": 3}}, {\"id\": \"saas-c0\", \"type\": \"card\", \"data\": {\"card_name\": \"Tenants & Subscriptions\", \"col\": 4}}, {\"id\": \"saas-c1\", \"type\": \"card\", \"data\": {\"card_name\": \"Provisioning\", \"col\": 4}}, {\"id\": \"saas-c2\", \"type\": \"card\", \"data\": {\"card_name\": \"Catalog & Billing\", \"col\": 4}}, {\"id\": \"saas-c3\", \"type\": \"card\", \"data\": {\"card_name\": \"Monitoring & Settings\", \"col\": 4}}]",
 "custom_blocks": [],
 "docstatus": 0,
 "doctype": "Workspace",
 "for_user": "",
 "hide_custom": 0,
 "icon": "es-line-cloud",
 "idx": 0,
 "is_hidden": 0,
 "label": "ERPGenex SaaS",
 "links": [
  {"hidden": 0, "is_query_report": 0, "label": "Tenants & Subscriptions", "link_count": 0, "onboard": 0, "type": "Card Break"},
  {"hidden": 0, "is_query_report": 0, "label": "SaaS Tenant", "link_count": 0, "link_to": "SaaS Tenant", "link_type": "DocType", "onboard": 0, "type": "Link"},
  {"hidden": 0, "is_query_report": 0, "label": "SaaS Subscription", "link_count": 0, "link_to": "SaaS Subscription", "link_type": "DocType", "onboard": 0, "type": "Link"},
  {"hidden": 0, "is_query_report": 0, "label": "SaaS Customer Account", "link_count": 0, "link_to": "SaaS Customer Account", "link_type": "DocType", "onboard": 0, "type": "Link"},
  {"hidden": 0, "is_query_report": 0, "label": "Provisioning", "link_count": 0, "onboard": 0, "type": "Card Break"},
  {"hidden": 0, "is_query_report": 0, "label": "Provisioning Request", "link_count": 0, "link_to": "Provisioning Request", "link_type": "DocType", "onboard": 0, "type": "Link"},
  {"hidden": 0, "is_query_report": 0, "label": "SaaS Domain", "link_count": 0, "link_to": "SaaS Domain", "link_type": "DocType", "onboard": 0, "type": "Link"},
  {"hidden": 0, "is_query_report": 0, "label": "Catalog & Billing", "link_count": 0, "onboard": 0, "type": "Card Break"},
  {"hidden": 0, "is_query_report": 0, "label": "SaaS Plan", "link_count": 0, "link_to": "SaaS Plan", "link_type": "DocType", "onboard": 0, "type": "Link"},
  {"hidden": 0, "is_query_report": 0, "label": "SaaS Package", "link_count": 0, "link_to": "SaaS Package", "link_type": "DocType", "onboard": 0, "type": "Link"},
  {"hidden": 0, "is_query_report": 0, "label": "SaaS Application", "link_count": 0, "link_to": "SaaS Application", "link_type": "DocType", "onboard": 0, "type": "Link"},
  {"hidden": 0, "is_query_report": 0, "label": "SaaS Invoice", "link_count": 0, "link_to": "SaaS Invoice", "link_type": "DocType", "onboard": 0, "type": "Link"},
  {"hidden": 0, "is_query_report": 0, "label": "SaaS Payment", "link_count": 0, "link_to": "SaaS Payment", "link_type": "DocType", "onboard": 0, "type": "Link"},
  {"hidden": 0, "is_query_report": 0, "label": "Monitoring & Settings", "link_count": 0, "onboard": 0, "type": "Card Break"},
  {"hidden": 0, "is_query_report": 0, "label": "SaaS Settings", "link_count": 0, "link_to": "SaaS Settings", "link_type": "DocType", "onboard": 0, "type": "Link"},
  {"hidden": 0, "is_query_report": 0, "label": "SaaS Usage Snapshot", "link_count": 0, "link_to": "SaaS Usage Snapshot", "link_type": "DocType", "onboard": 0, "type": "Link"},
  {"hidden": 0, "is_query_report": 0, "label": "SaaS Audit Log", "link_count": 0, "link_to": "SaaS Audit Log", "link_type": "DocType", "onboard": 0, "type": "Link"},
  {"hidden": 0, "is_query_report": 0, "label": "SaaS Notification Log", "link_count": 0, "link_to": "SaaS Notification Log", "link_type": "DocType", "onboard": 0, "type": "Link"}
 ],
 "modified": "2026-07-08 17:10:00",
 "modified_by": "Administrator",
 "module": "ERPGenex SaaS",
 "name": "ERPGenex SaaS",
 "number_cards": [],
 "owner": "Administrator",
 "parent_page": "",
 "public": 1,
 "quick_lists": [],
 "restrict_to_domain": "",
 "roles": [],
 "sequence_id": 1.0,
 "shortcuts": [
  {"color": "Blue", "doc_view": "List", "icon": "es-line-people", "label": "SaaS Tenant", "link_to": "SaaS Tenant", "type": "DocType"},
  {"color": "Green", "doc_view": "List", "icon": "es-line-link", "label": "SaaS Subscription", "link_to": "SaaS Subscription", "type": "DocType"},
  {"color": "Orange", "doc_view": "List", "icon": "es-line-inbox", "label": "Provisioning Request", "link_to": "Provisioning Request", "type": "DocType"},
  {"color": "Purple", "doc_view": "List", "icon": "es-line-template", "label": "SaaS Plan", "link_to": "SaaS Plan", "type": "DocType"},
  {"color": "Cyan", "doc_view": "List", "icon": "es-line-filetype", "label": "SaaS Application", "link_to": "SaaS Application", "type": "DocType"},
  {"color": "Grey", "doc_view": "Form", "icon": "es-line-settings", "label": "SaaS Settings", "link_to": "SaaS Settings", "type": "DocType"}
 ],
 "title": "ERPGenex SaaS"
}
